duckduckgo_search/version.py
duckduckgo_search/__init__.py
duckduckgo_search/cli.py
duckduckgo_search/utils.py
duckduckgo_search/py.typed
duckduckgo_search/exceptions.py
duckduckgo_search/__main__.py
duckduckgo_search/duckduckgo_search.py
duckduckgo_search/libs/utils_chat.cpython-39-darwin.so
duckduckgo_search/libs/utils_chat__mypyc.cpython-39-darwin.so
duckduckgo_search-2025.4.4.dist-info/RECORD
duckduckgo_search-2025.4.4.dist-info/WHEEL
duckduckgo_search-2025.4.4.dist-info/entry_points.txt
duckduckgo_search-2025.4.4.dist-info/top_level.txt
duckduckgo_search-2025.4.4.dist-info/METADATA
duckduckgo_search-2025.4.4.dist-info/licenses/LICENSE.md
