Metadata-Version: 2.4
Name: duckduckgo_search
Version: 2025.4.4
Summary: Search for words, documents, images, news, maps and text translation using the DuckDuckGo.com search engine.
Author: deedy5
License-Expression: MIT
Project-URL: Homepage, https://github.com/deedy5/duckduckgo_search
Keywords: python,duckduckgo
Classifier: Development Status :: 5 - Production/Stable
Classifier: Operating System :: OS Independent
Classifier: Programming Language :: Python :: 3
Classifier: Programming Language :: Python :: 3 :: Only
Classifier: Programming Language :: Python :: 3.9
Classifier: Programming Language :: Python :: 3.10
Classifier: Programming Language :: Python :: 3.11
Classifier: Programming Language :: Python :: 3.12
Classifier: Programming Language :: Python :: 3.13
Classifier: Programming Language :: Python :: Implementation :: CPython
Classifier: Topic :: Internet :: WWW/HTTP :: Indexing/Search
Classifier: Topic :: Software Development :: Libraries :: Python Modules
Requires-Python: >=3.9
License-File: LICENSE.md
Requires-Dist: click>=8.1.8
Requires-Dist: primp>=0.14.0
Requires-Dist: lxml>=5.3.0
Provides-Extra: chat
Requires-Dist: stpyv8>=13.1.201.22; extra == "chat"
Provides-Extra: dev
Requires-Dist: mypy[mypyc]>=1.15.0; extra == "dev"
Requires-Dist: orjson>=3.10.16; extra == "dev"
Requires-Dist: pytest>=8.3.4; extra == "dev"
Requires-Dist: pytest-dependency>=0.6.0; extra == "dev"
Requires-Dist: ruff>=0.11.2; extra == "dev"
Requires-Dist: lxml-stubs>=0.5.1; extra == "dev"
Requires-Dist: types-setuptools>=78.1.0.20250329; extra == "dev"
Dynamic: license-file
